libdogecoin.cpython-310-darwin.so
tests/__init__.py
tests/address_test.py
tests/transaction_test.py
libdogecoin-0.1.0.post1.dist-info/LICENSE
libdogecoin-0.1.0.post1.dist-info/METADATA
libdogecoin-0.1.0.post1.dist-info/WHEEL
libdogecoin-0.1.0.post1.dist-info/top_level.txt
libdogecoin-0.1.0.post1.dist-info/RECORD
