Metadata-Version: 2.1
Name: libdogecoin
Version: 0.1.0.post1
Summary: Python interface for the libdogecoin C library
Home-page: https://github.com/dogecoinfoundation/libdogecoin
Author: Jackie McAninch
Author-email: jackie.mcaninch.2019@gmail.com
Maintainer: bluezr
Maintainer-email: bluezr@dogecoin.com
License: AGPL-3.0
Classifier: Programming Language :: Python :: 3
Classifier: License :: OSI Approved :: MIT License
Classifier: Operating System :: POSIX :: Linux
License-File: LICENSE
